{
  "lookupKey": "DepreciationFrequency",
  "name": "Depreciation Frequency",
  "isSystem": true,
  "values": [
    {
      "code": "0",
      "name": "Monthly",
      "sortOrder": 1,
      "isActive": true
    },
    {
      "code": "1",
      "name": "Quarterly",
      "sortOrder": 2,
      "isActive": true
    },
    {
      "code": "2",
      "name": "Semi-Annual",
      "sortOrder": 3,
      "isActive": true
    },
    {
      "code": "3",
      "name": "Annual",
      "sortOrder": 4,
      "isActive": true
    },
    {
      "code": "4",
      "name": "Custom",
      "sortOrder": 5,
      "isActive": true
    }
  ]
}
